{"registration_form":{"name":"name1","email":"email1","password":"123","address":"zarubina","_token":"EJ1YEUnyuwGKoNWNBJ2wCQfruMS27TkTn6lSU24aoUk"}}
{"registration_form":{"name":"name2","email":"email2","password":"12345","address":"zarubina123","_token":"EJ1YEUnyuwGKoNWNBJ2wCQfruMS27TkTn6lSU24aoUk"}}
{"registration_form":{"name":"name2","email":"email2","password":"12345","address":"zarubina123","_token":"EJ1YEUnyuwGKoNWNBJ2wCQfruMS27TkTn6lSU24aoUk"}}
{"registration_form":{"name":"hello","email":"mail","password":"1234","address":"zarubina","_token":"EJ1YEUnyuwGKoNWNBJ2wCQfruMS27TkTn6lSU24aoUk"}}
{"registration_form":{"name":"user1","email":"mail.2","password":"12333","address":"lenina","_token":"EJ1YEUnyuwGKoNWNBJ2wCQfruMS27TkTn6lSU24aoUk"}}
